anastruct/__init__.py
anastruct/basic.py
anastruct/py.typed
anastruct/types.py
anastruct/vertex.py
anastruct/cython/__init__.py
anastruct/cython/basic.py
anastruct/cython/cbasic.cpython-311-aarch64-linux-gnu.so
anastruct/cython/cbasic.pyx
anastruct/fem/__init__.py
anastruct/fem/elements.py
anastruct/fem/node.py
anastruct/fem/postprocess.py
anastruct/fem/system.py
anastruct/fem/cython/__init__.py
anastruct/fem/cython/celements.cpython-311-aarch64-linux-gnu.so
anastruct/fem/cython/celements.pyx
anastruct/fem/cython/elements.py
anastruct/fem/examples/__init__.py
anastruct/fem/examples/ex_1.py
anastruct/fem/examples/ex_10_dead_load.py
anastruct/fem/examples/ex_11.py
anastruct/fem/examples/ex_12.py
anastruct/fem/examples/ex_13.py
anastruct/fem/examples/ex_14.py
anastruct/fem/examples/ex_15.py
anastruct/fem/examples/ex_16.py
anastruct/fem/examples/ex_17_gnl.py
anastruct/fem/examples/ex_18_discretize.py
anastruct/fem/examples/ex_19_num_displacements.py
anastruct/fem/examples/ex_1_2.py
anastruct/fem/examples/ex_2.py
anastruct/fem/examples/ex_20_insert_node.py
anastruct/fem/examples/ex_21_rotate_force.py
anastruct/fem/examples/ex_22_loadcombination_doc.py
anastruct/fem/examples/ex_23_sectionbase.py
anastruct/fem/examples/ex_24_envelope_lines.py
anastruct/fem/examples/ex_25_high_midspan_point.py
anastruct/fem/examples/ex_26_deflection.py
anastruct/fem/examples/ex_3.py
anastruct/fem/examples/ex_4.py
anastruct/fem/examples/ex_5.py
anastruct/fem/examples/ex_6_fixed_hinge.py
anastruct/fem/examples/ex_7_rotational_spring.py
anastruct/fem/examples/ex_8_non_linear_portal.py
anastruct/fem/examples/ex_9_vertical_spring.py
anastruct/fem/examples/water_acc.ipynb
anastruct/fem/plotter/__init__.py
anastruct/fem/plotter/element.py
anastruct/fem/plotter/mpl.py
anastruct/fem/plotter/null.py
anastruct/fem/plotter/values.py
anastruct/fem/system_components/__init__.py
anastruct/fem/system_components/assembly.py
anastruct-1.6.2.dist-info/METADATA
anastruct-1.6.2.dist-info/WHEEL
anastruct-1.6.2.dist-info/RECORD
anastruct-1.6.2.dist-info/licenses/LICENSE.txt
