Metadata-Version: 2.4
Name: anastruct
Version: 1.6.2
Summary: Finite element analysis of 2D structures
License: GPL-3.0-or-later
License-File: LICENSE.txt
Keywords: FEA,finite element,structural engineering,structural analysis
Author: Ritchie Vink
Author-email: ritchie46@gmail.com
Maintainer: Brooks Smith
Maintainer-email: smith120bh@gmail.com
Requires-Python: >=3.10
Classifier: Development Status :: 5 - Production/Stable
Classifier: Intended Audience :: Science/Research
Classifier: License :: OSI Approved :: GNU General Public License v3 (GPLv3)
Classifier: License :: OSI Approved :: GNU General Public License v3 or later (GPLv3+)
Classifier: Programming Language :: Python :: 3
Classifier: Programming Language :: Python :: 3.10
Classifier: Programming Language :: Python :: 3.11
Classifier: Programming Language :: Python :: 3.12
Classifier: Programming Language :: Python :: 3.13
Classifier: Programming Language :: Python :: 3.14
Classifier: Topic :: Scientific/Engineering
Classifier: Topic :: Scientific/Engineering :: Physics
Classifier: Topic :: Software Development :: Libraries :: Python Modules
Provides-Extra: plot
Requires-Dist: matplotlib (>=3.0) ; extra == "plot"
Requires-Dist: numpy (>=1.23.5)
Requires-Dist: scipy (>=1.10.0)
Project-URL: Documentation, http://anastruct.readthedocs.io
Project-URL: Homepage, https://github.com/ritchie46/anaStruct
Project-URL: Repository, https://github.com/ritchie46/anaStruct
